wordlist/__init__.py
wordlist/main.py
wordlist_tool-1.0.3.dist-info/licenses/LICENSE
wordlist_tool-1.0.3.dist-info/METADATA
wordlist_tool-1.0.3.dist-info/WHEEL
wordlist_tool-1.0.3.dist-info/entry_points.txt
wordlist_tool-1.0.3.dist-info/top_level.txt
wordlist_tool-1.0.3.dist-info/RECORD
