Metadata-Version: 2.4
Name: wordlist-tool
Version: 1.0.3
Summary: A word list generator tool
Author: Raman
Requires-Python: >=3.8
License-File: LICENSE
Dynamic: license-file
